iiif_now/__init__.py
iiif_now/csvreader/__init__.py
iiif_now/csvreader/csvreader.py
iiif_now/datacanvas/__init__.py
iiif_now/datacanvas/datacanvas.py
iiif_now/homepage/__init__.py
iiif_now/homepage/homepage.py
iiif_now/iiifnow.py
iiif_now/manifest/__init__.py
iiif_now/manifest/manifest.py
iiif_now/navplace/__init__.py
iiif_now/navplace/navplace.py
iiif_now/study_guide/__init__.py
iiif_now/study_guide/study_guide.py
iiif_now/thumbnail/__init__.py
iiif_now/thumbnail/thumbnail.py
iiif_now-0.1.6.dist-info/METADATA
iiif_now-0.1.6.dist-info/WHEEL
iiif_now-0.1.6.dist-info/entry_points.txt
iiif_now-0.1.6.dist-info/RECORD
